jmp/__init__.py
jmp/loss_scale.py
jmp/policy.py
jamp-0.0.6.dist-info/METADATA
jamp-0.0.6.dist-info/WHEEL
jamp-0.0.6.dist-info/licenses/LICENSE
jamp-0.0.6.dist-info/RECORD
