Metadata-Version: 2.3
Name: jamp
Version: 0.0.6
Summary: JAMP is a Mixed Precision library for JAX. Forked from DeepMind's JMP.
Author-email: DeepMind <jmp-dev-os@google.com>, Clement POIRET <poiret.clement@outlook.fr>
License: 
License-File: LICENSE
Requires-Python: >=3.10
Requires-Dist: jax>=0.4.17
Requires-Dist: numpy>=1.26
